{"cameraMode":{"drawMode":0,"name":"Shaded","section":"Shading Mode"},"sceneLighting":true,"audioPlay":false,"sceneViewState":{"m_AlwaysRefresh":false,"showFog":true,"showSkybox":true,"showFlares":true,"showImageEffects":true,"showParticleSystems":true,"showVisualEffectGraphs":true,"m_FxEnabled":true},"in2DMode":false,"pivot":{"x":-4.310068130493164,"y":-5.201042175292969,"z":15.153078079223633},"rotation":{"x":-0.22596411406993867,"y":0.6986071467399597,"z":-0.2501218318939209,"w":-0.6311330199241638},"size":18.519447326660158,"orthographic":false}